setup.py
restack/__init__.py
restack/connection.py
restack/entities.py
restack/exceptions.py
restack/mocks.py
restack/tests.py
restack.egg-info/PKG-INFO
restack.egg-info/SOURCES.txt
restack.egg-info/dependency_links.txt
restack.egg-info/top_level.txt