Metadata-Version: 1.1
Name: restack
Version: 0.0.1a
Summary: A wrapper for working with Restack, the API for IoT communication
Home-page: https://github.com/lepoetemaudit/restack
Author: Dave Jeffrey
Author-email: mail@davidjeffrey.co.uk
License: BSD
Keywords: restack IoT
Platform: UNKNOWN
Classifier: Development Status :: 3 - Alpha
Classifier: License :: OSI Approved :: BSD License
